scapy2dict.py
scapy2dict-0.11.dist-info/DESCRIPTION.rst
scapy2dict-0.11.dist-info/METADATA
scapy2dict-0.11.dist-info/RECORD
scapy2dict-0.11.dist-info/WHEEL
scapy2dict-0.11.dist-info/metadata.json
scapy2dict-0.11.dist-info/top_level.txt
